{  
   "type":"FeatureCollection",
   "features":[  
      {  
         "type":"Feature",
         "properties":{  
            "Ilivehere":"false",
            "PlaceName":"Newark"
         },
         "geometry":{  
            "type":"Point",
            "coordinates":[  
               -73.970947265625,
               40.77846164090355
            ]
         }
      },
      {  
         "type":"Feature",
         "properties":{  
            "Ilivehere":"true",
            "PlaceName":"Brooklyn"
         },
         "geometry":{  
            "type":"Point",
            "coordinates":[  
               -74.16664123535156,
               40.73216945026674
            ]
         }
      },
      {  
         "type":"Feature",
         "properties":{  
            "PlaceName":""
         },
         "geometry":{  
            "type":"Point",
            "coordinates":[  
               -73.90914916992188,
               40.70979201243495
            ]
         }
      }
   ]
}